guilab.py
guilab-0.1.0.dist-info/METADATA
guilab-0.1.0.dist-info/WHEEL
guilab-0.1.0.dist-info/top_level.txt
guilab-0.1.0.dist-info/RECORD
