Metadata-Version: 2.4
Name: GUILab
Version: 0.1.0
Summary: A lightweight Python GUI library for building applications quickly.
Author-email: Ibrahim <ibrahimshahid7767@gmail.com>
License-Expression: MIT
Keywords: gui,python,ttkbootstrap,tkinter,GUILab
Classifier: Programming Language :: Python :: 3
Classifier: Operating System :: OS Independent
Requires-Python: >=3.7
